a4agro_vegetation_index_v2/__init__.py
a4agro_vegetation_index_v2/colorsmaps.py
a4agro_vegetation_index_v2/constants.py
a4agro_vegetation_index_v2/exceptions.py
a4agro_vegetation_index_v2/index_calculation.py
a4agro_vegetation_index_v2/plot_generation.py
a4agro_vegetation_index_v2-1.1.0.dist-info/METADATA
a4agro_vegetation_index_v2-1.1.0.dist-info/WHEEL
a4agro_vegetation_index_v2-1.1.0.dist-info/top_level.txt
a4agro_vegetation_index_v2-1.1.0.dist-info/RECORD
