Metadata-Version: 2.1
Name: a4agro-vegetation-index-v2
Version: 1.1.0
Summary: This is a package for a4agro vegetation index calculation and generation of figures
Home-page: UNKNOWN
Author: a4agrodevops
Author-email: devops.a4agro@gmail.com
License: UNKNOWN
Keywords: vegetation,index,a4agro
Platform: UNKNOWN
Classifier: Development Status :: 3 - Alpha
Classifier: Intended Audience :: Developers
Classifier: Topic :: Software Development :: Build Tools
Classifier: License :: OSI Approved :: MIT License
Classifier: Programming Language :: Python :: 3.12
Requires-Dist: numpy
Requires-Dist: matplotlib
Requires-Dist: rasterio
Requires-Dist: scipy
Requires-Dist: PyQt6
Requires-Dist: scikit-image
